cwtlib/__init__.py
cwtlib/ro_norm.py
cwtlib/tests.py
cwtlib/tower.py
cwtlib/water.py
cwtlib/units/__init__.py
cwtlib/units/area_unit.py
cwtlib/units/density_unit.py
cwtlib/units/flow_rate_unit.py
cwtlib/units/heat_unit.py
cwtlib/units/humidity_unit.py
cwtlib/units/ion.py
cwtlib/units/power_unit.py
cwtlib/units/pressure_unit.py
cwtlib/units/rate_unit.py
cwtlib/units/tds_unit.py
cwtlib/units/temp_unit.py
cwtlib/units/time_unit.py
cwtlib/units/unit.py
cwtlib/units/volume_unit.py
cwtlib-0.11.dist-info/LICENSE
cwtlib-0.11.dist-info/METADATA
cwtlib-0.11.dist-info/WHEEL
cwtlib-0.11.dist-info/top_level.txt
cwtlib-0.11.dist-info/RECORD
