Metadata-Version: 2.1
Name: cwtlib
Version: 0.11
Summary: A package for working with the basic calculations of the CWT, RO
Home-page: https://github.com/fscontrol/cwtlib
Author: Dmitrii Babaev
Author-email: babaevdmitri@gmail.com
License-File: LICENSE
Requires-Dist: numpy >=1.18.1
Requires-Dist: requests >=2.22.0
